langrade/__init__.py
langrade/constants.py
langrade/embeddings.py
langrade/grader.py
langrade/providers.py
langrade/retriever.py
langrade-0.1.5.dist-info/METADATA
langrade-0.1.5.dist-info/WHEEL
langrade-0.1.5.dist-info/entry_points.txt
langrade-0.1.5.dist-info/RECORD
