Metadata-Version: 2.1
Name: langrade
Version: 0.1.5
Summary: A library for grading documents using LLMs
License: MIT
Author: nisaji
Author-email: nisaji27@gmail.com
Requires-Python: >=3.9,<4.0
Classifier: License :: OSI Approved :: MIT License
Classifier: Programming Language :: Python :: 3
Classifier: Programming Language :: Python :: 3.9
Classifier: Programming Language :: Python :: 3.10
Classifier: Programming Language :: Python :: 3.11
Classifier: Programming Language :: Python :: 3.12
Requires-Dist: beautifulsoup4 (>=4.12.0,<5.0.0)
Requires-Dist: langchain (>=0.2.6,<0.3.0)
Requires-Dist: langchain-anthropic (>=0.1.20,<0.2.0)
Requires-Dist: langchain-community (>=0.2.6,<0.3.0)
Requires-Dist: langchain-core (>=0.2.11,<0.3.0)
Requires-Dist: langchain-google-genai (>=1.0.7,<2.0.0)
Requires-Dist: langchain-openai (>=0.1.14,<0.2.0)
Requires-Dist: numpy (>=1.24.0,<2.0.0)
Requires-Dist: python-dotenv (>=1.0.0,<2.0.0)
Requires-Dist: vertexai (>=1.71.1,<2.0.0)
